django_node_modules/__init__.py
django_node_modules/apps.py
django_node_modules/constants.py
django_node_modules/urls.py
django_node_modules/views.py
django_node_modules/templates/django_node_modules/includes/local_node_packages.html
django_node_modules/templates/django_node_modules/includes/npm_node_packages.html
django_node_modules/templates/django_node_modules/includes/hrenpack/css.html
django_node_modules/templates/django_node_modules/includes/hrenpack/hrenpack-theme-style.html
django_node_modules/templates/django_node_modules/includes/hrenpack/hrenpack_js.html
django_node_modules/templates/django_node_modules/includes/hrenpack/hts-css.html
django_node_modules/templatetags/__init__.py
django_node_modules/templatetags/node_hrenpack.py
django_node_modules/templatetags/node_modules.py
django_node_modules/utils/__init__.py
django_node_modules/utils/base.py
django_node_modules/utils/hrenpack_base.py
django_node_modules/utils/hrenpack_js.py
django_node_modules/utils/hrenpack_theme_style.py
django_node_modules-1.0.6.dist-info/licenses/LICENSE
django_node_modules-1.0.6.dist-info/METADATA
django_node_modules-1.0.6.dist-info/WHEEL
django_node_modules-1.0.6.dist-info/top_level.txt
django_node_modules-1.0.6.dist-info/RECORD
