Metadata-Version: 2.4
Name: django-node-modules
Version: 1.0.6
Summary: A Django application for easily managing and serving files from local node_modules and remote NPM packages directly from Django templates
Home-page: https://github.com/magilyasdoma/django-node-modules
Author: Маг Ильяс DOMA (MagIlyasDOMA)
Author-email: magilyas.doma.09@list.ru
License: MIT
Project-URL: Source, https://github.com/magilyasdoma/django-node-modules
Project-URL: Documentation, https://github.com/magilyasdoma/django-node-modules/README.md
Project-URL: Tracker, https://github.com/magilyasdoma/django-node-modules/issues
Keywords: django,node.js,node,nodejs,npm,static
Classifier: Development Status :: 5 - Production/Stable
Classifier: Intended Audience :: Developers
Classifier: Intended Audience :: System Administrators
Classifier: Intended Audience :: Information Technology
Classifier: License :: OSI Approved :: MIT License
Classifier: Operating System :: OS Independent
Classifier: Programming Language :: Python
Classifier: Programming Language :: Python :: 3
Classifier: Programming Language :: Python :: 3.10
Classifier: Programming Language :: Python :: 3.11
Classifier: Programming Language :: Python :: 3.12
Classifier: Programming Language :: Python :: 3.13
Classifier: Programming Language :: Python :: 3.14
Classifier: Framework :: Django
Classifier: Framework :: Django :: 5.2
Classifier: Topic :: Text Processing :: Markup
Classifier: Topic :: Text Processing :: Markup :: HTML
Requires-Python: >=3.10
License-File: LICENSE
Requires-Dist: filetype>=1.2.0
Requires-Dist: django>=5.2.9
Requires-Dist: django-static-engine<0.2.0,>=0.1.8
Requires-Dist: requests
Dynamic: author
Dynamic: author-email
Dynamic: classifier
Dynamic: description
Dynamic: description-content-type
Dynamic: home-page
Dynamic: keywords
Dynamic: license
Dynamic: license-file
Dynamic: project-url
Dynamic: requires-dist
Dynamic: requires-python
Dynamic: summary
